stargazers_scraper/__init__.py
stargazers_scraper/constants.py
stargazers_scraper/exceptions.py
stargazers_scraper/extractors.py
stargazers_scraper/logging_config.py
stargazers_scraper/main.py
stargazers_scraper-0.1.0.dist-info/licenses/LICENSE
stargazers_scraper-0.1.0.dist-info/METADATA
stargazers_scraper-0.1.0.dist-info/WHEEL
stargazers_scraper-0.1.0.dist-info/top_level.txt
stargazers_scraper-0.1.0.dist-info/RECORD
