Metadata-Version: 2.4
Name: stargazers-scraper
Version: 0.1.0
Summary: Scrape stargazers from a GitHub repository.
Author-email: Jona Schwarz <jona.schwarz@code.berlin>
License: MIT
Project-URL: Homepage, https://github.com/jschwarz/stargazers-scraper
Project-URL: Repository, https://github.com/jschwarz/stargazers-scraper.git
Keywords: github,scraper,stargazers
Classifier: Development Status :: 3 - Alpha
Classifier: Intended Audience :: Developers
Classifier: License :: OSI Approved :: MIT License
Classifier: Operating System :: OS Independent
Classifier: Programming Language :: Python :: 3
Classifier: Programming Language :: Python :: 3.7
Classifier: Programming Language :: Python :: 3.8
Classifier: Programming Language :: Python :: 3.9
Classifier: Programming Language :: Python :: 3.10
Classifier: Programming Language :: Python :: 3.11
Requires-Python: >=3.7
License-File: LICENSE
Requires-Dist: requests>=2.25.0
Requires-Dist: beautifulsoup4>=4.9.3
Provides-Extra: dev
Provides-Extra: docs
Dynamic: license-file
